MANIFEST.in
README.md
setup.py
mkeditor/__init__.py
mkeditor/admin.py
mkeditor/apps.py
mkeditor/models.py
mkeditor/settings.py
mkeditor/tests.py
mkeditor/widgets.py
mkeditor.egg-info/PKG-INFO
mkeditor.egg-info/SOURCES.txt
mkeditor.egg-info/dependency_links.txt
mkeditor.egg-info/top_level.txt
mkeditor/static/.DS_Store
mkeditor/static/css/.DS_Store
mkeditor/static/css/editormd.css
mkeditor/static/css/style.css
mkeditor/static/fonts/FontAwesome.otf
mkeditor/static/fonts/editormd-logo.eot
mkeditor/static/fonts/editormd-logo.svg
mkeditor/static/fonts/editormd-logo.ttf
mkeditor/static/fonts/editormd-logo.woff
mkeditor/static/fonts/fontawesome-webfont.eot
mkeditor/static/fonts/fontawesome-webfont.svg
mkeditor/static/fonts/fontawesome-webfont.ttf
mkeditor/static/fonts/fontawesome-webfont.woff
mkeditor/static/fonts/fontawesome-webfont.woff2
mkeditor/static/images/loading.gif
mkeditor/static/js/.DS_Store
mkeditor/static/js/editormd.js
mkeditor/static/js/jquery.min.js
mkeditor/static/lib/.DS_Store
mkeditor/static/lib/flowchart.min.js
mkeditor/static/lib/jquery.flowchart.min.js
mkeditor/static/lib/marked.min.js
mkeditor/static/lib/prettify.min.js
mkeditor/static/lib/raphael.min.js
mkeditor/static/lib/sequence-diagram.min.js
mkeditor/static/lib/underscore.min.js
mkeditor/static/lib/codemirror/AUTHORS
mkeditor/static/lib/codemirror/LICENSE
mkeditor/static/lib/codemirror/README.md
mkeditor/static/lib/codemirror/addons.min.js
mkeditor/static/lib/codemirror/bower.json
mkeditor/static/lib/codemirror/codemirror.min.css
mkeditor/static/lib/codemirror/codemirror.min.js
mkeditor/static/lib/codemirror/modes.min.js
mkeditor/static/lib/codemirror/package.json
mkeditor/static/lib/codemirror/addon/comment/comment.js
mkeditor/static/lib/codemirror/addon/comment/continuecomment.js
mkeditor/static/lib/codemirror/addon/dialog/dialog.css
mkeditor/static/lib/codemirror/addon/dialog/dialog.js
mkeditor/static/lib/codemirror/addon/display/fullscreen.css
mkeditor/static/lib/codemirror/addon/display/fullscreen.js
mkeditor/static/lib/codemirror/addon/display/panel.js
mkeditor/static/lib/codemirror/addon/display/placeholder.js
